Metadata-Version: 2.1
Name: StealerDiscord
Version: 1.4
Summary: A simple package to make an discord stealer with python
Home-page: https://discord.gg/tRgE7eFTkt
Author: ['VMS_SHOP', 'yashing2', 'phantoms_._']
Author-email: discordyashing@gmail.com
Classifier: Environment :: Win32 (MS Windows)
Classifier: Natural Language :: French
Classifier: Operating System :: Microsoft :: Windows :: Windows 10
Classifier: Operating System :: Microsoft :: Windows :: Windows 11
Classifier: Programming Language :: Python :: 3.10
Classifier: Programming Language :: Python :: 3.11
Classifier: Programming Language :: Python :: 3.12
Classifier: Programming Language :: Python :: 3.13
Classifier: Topic :: System
Classifier: Topic :: System :: Logging
Requires-Python: >=3.10
License-File: LICENCE
Requires-Dist: pycryptodome
Requires-Dist: requests
Requires-Dist: vpo
Requires-Dist: pillow
Requires-Dist: datetime
Requires-Dist: psutil
Requires-Dist: sqlite3
Requires-Dist: pywin32
